Metadata-Version: 2.1
Name: python-polymorphism
Version: 0.1.0
Summary: A simple utility library that allow you to use OOP Like Polymorphic Function in python
Home-page: https://github.com/KiraPC/python-polymorphism
Author: Pasquale Carmine Carbone
Author-email: pasqualecarmine.carbone@gmail.com
License: UNKNOWN
Platform: UNKNOWN
Classifier: Programming Language :: Python :: 3
Classifier: License :: OSI Approved :: MIT License
Classifier: Operating System :: OS Independent
Classifier: Topic :: Software Development :: Libraries :: Python Modules
Classifier: Topic :: Software Development :: Libraries
Classifier: Topic :: Software Development
Classifier: Typing :: Typed
Requires-Python: >=3.6
